odoo10_addon_partner_contact_company-10.0.1.0.1-nspkg.pth
odoo/addons/partner_contact_company/README.rst
odoo/addons/partner_contact_company/__init__.py
odoo/addons/partner_contact_company/__manifest__.py
odoo/addons/partner_contact_company/demo/partner.xml
odoo/addons/partner_contact_company/models/__init__.py
odoo/addons/partner_contact_company/models/partner.py
odoo/addons/partner_contact_company/tests/__init__.py
odoo/addons/partner_contact_company/tests/test_partner.py
odoo/addons/partner_contact_company/views/partner_view.xml
odoo/addons/partner_contact_company/views/users_view.xml
odoo10_addon_partner_contact_company-10.0.1.0.1.dist-info/METADATA
odoo10_addon_partner_contact_company-10.0.1.0.1.dist-info/WHEEL
odoo10_addon_partner_contact_company-10.0.1.0.1.dist-info/namespace_packages.txt
odoo10_addon_partner_contact_company-10.0.1.0.1.dist-info/top_level.txt
odoo10_addon_partner_contact_company-10.0.1.0.1.dist-info/RECORD
